[
  {
    "name": "Statistical Baseline",
    "n_params": 14,
    "test_accuracy": 0.5240451388888889,
    "test_f1": 0.5578575258597586,
    "detection_rate": 0.2793601248536871,
    "false_alarm": 0.32957463436418444,
    "training_time": 0.7342033386230469,
    "best_val_f1": 0.0,
    "key": "baseline"
  },
  {
    "name": "LSTM v2a (baseline config)",
    "n_params": 534279,
    "test_accuracy": 0.2798611111111111,
    "test_f1": 0.34941712274007347,
    "detection_rate": 0.9391785150078988,
    "false_alarm": 0.6934731934731935,
    "training_time": 13.944255352020264,
    "best_val_f1": 0.4763035588521859,
    "key": "lstm_v2a"
  },
  {
    "name": "LSTM v2b (larger, slower LR)",
    "n_params": 2082439,
    "test_accuracy": 0.35703125,
    "test_f1": 0.3994828857907799,
    "detection_rate": 0.8931016324381253,
    "false_alarm": 0.6232841232841233,
    "training_time": 46.23941445350647,
    "best_val_f1": 0.5127791045249249,
    "key": "lstm_v2b"
  },
  {
    "name": "LSTM v2c (small, fast)",
    "n_params": 136071,
    "test_accuracy": 0.24097222222222223,
    "test_f1": 0.273226862551719,
    "detection_rate": 0.8775671406003159,
    "false_alarm": 0.7707847707847708,
    "training_time": 9.778470754623413,
    "best_val_f1": 0.4855650238522899,
    "key": "lstm_v2c"
  },
  {
    "name": "Transformer v1a (baseline)",
    "n_params": 150855,
    "test_accuracy": 0.42256944444444444,
    "test_f1": 0.4660129889252831,
    "detection_rate": 0.8399157451290152,
    "false_alarm": 0.5209790209790209,
    "training_time": 25.579756498336792,
    "best_val_f1": 0.5778165731726459,
    "key": "transformer_v1a"
  },
  {
    "name": "Transformer v1b (deeper)",
    "n_params": 200839,
    "test_accuracy": 0.2947916666666667,
    "test_f1": 0.3564829331896084,
    "detection_rate": 0.9233807266982622,
    "false_alarm": 0.6876456876456877,
    "training_time": 30.473612070083618,
    "best_val_f1": 0.4457284345670553,
    "key": "transformer_v1b"
  },
  {
    "name": "Transformer v1c (wider)",
    "n_params": 398343,
    "test_accuracy": 0.44609375,
    "test_f1": 0.5019959116614209,
    "detection_rate": 0.8014744602422328,
    "false_alarm": 0.4621859621859622,
    "training_time": 14.041764974594116,
    "best_val_f1": 0.5874882029349882,
    "key": "transformer_v1c"
  },
  {
    "name": "Hierarchical v1a (baseline)",
    "n_params": 534279,
    "test_accuracy": 0.34913194444444445,
    "test_f1": 0.3833704054546215,
    "detection_rate": 0.8601895734597157,
    "false_alarm": 0.6280756280756281,
    "training_time": 9.301774501800537,
    "best_val_f1": 0.4482816775161834,
    "key": "hierarchical_v1a"
  },
  {
    "name": "Hierarchical v1b (larger)",
    "n_params": 2082439,
    "test_accuracy": 0.33428819444444446,
    "test_f1": 0.40884345306387215,
    "detection_rate": 0.8730911005792522,
    "false_alarm": 0.65009065009065,
    "training_time": 50.64207100868225,
    "best_val_f1": 0.5129255309846441,
    "key": "hierarchical_v1b"
  }
]